src/__init__.py
src/workflow.py
src/agents/__init__.py
src/agents/agents.py
src/config/__init__.py
src/config/agents.py
src/config/configuration.py
src/config/loader.py
src/config/questions.py
src/config/report_style.py
src/config/tools.py
src/crawler/__init__.py
src/crawler/article.py
src/crawler/crawler.py
src/crawler/jina_client.py
src/crawler/readability_extractor.py
src/graph/__init__.py
src/graph/builder.py
src/graph/checkpoint.py
src/graph/nodes.py
src/graph/types.py
src/llms/__init__.py
src/llms/llm.py
src/llms/providers/dashscope.py
src/podcast/types.py
src/podcast/graph/audio_mixer_node.py
src/podcast/graph/builder.py
src/podcast/graph/script_writer_node.py
src/podcast/graph/state.py
src/podcast/graph/tts_node.py
src/ppt/graph/builder.py
src/ppt/graph/ppt_composer_node.py
src/ppt/graph/ppt_generator_node.py
src/ppt/graph/state.py
src/prompt_enhancer/__init__.py
src/prompt_enhancer/graph/builder.py
src/prompt_enhancer/graph/enhancer_node.py
src/prompt_enhancer/graph/state.py
src/prompts/__init__.py
src/prompts/coder.md
src/prompts/coordinator.md
src/prompts/planner.md
src/prompts/planner_model.py
src/prompts/reporter.md
src/prompts/researcher.md
src/prompts/template.py
src/prompts/podcast/podcast_script_writer.md
src/prompts/ppt/ppt_composer.md
src/prompts/prompt_enhancer/prompt_enhancer.md
src/prompts/prose/prose_continue.md
src/prompts/prose/prose_fix.md
src/prompts/prose/prose_improver.md
src/prompts/prose/prose_longer.md
src/prompts/prose/prose_shorter.md
src/prompts/prose/prose_zap.md
src/prose/graph/builder.py
src/prose/graph/prose_continue_node.py
src/prose/graph/prose_fix_node.py
src/prose/graph/prose_improve_node.py
src/prose/graph/prose_longer_node.py
src/prose/graph/prose_shorter_node.py
src/prose/graph/prose_zap_node.py
src/prose/graph/state.py
src/rag/__init__.py
src/rag/builder.py
src/rag/ragflow.py
src/rag/retriever.py
src/rag/vikingdb_knowledge_base.py
src/server/__init__.py
src/server/app.py
src/server/chat_request.py
mseep_deer_flow-0.1.1.dist-info/METADATA
mseep_deer_flow-0.1.1.dist-info/WHEEL
mseep_deer_flow-0.1.1.dist-info/entry_points.txt
mseep_deer_flow-0.1.1.dist-info/licenses/LICENSE
mseep_deer_flow-0.1.1.dist-info/RECORD
