Metadata-Version: 2.4
Name: mseep-deer-flow
Version: 0.1.1
Summary: DeerFlow project
Author-email: mseep <support@skydeck.ai>
License-File: LICENSE
Requires-Python: >=3.12
Requires-Dist: arxiv>=2.2.0
Requires-Dist: duckduckgo-search>=8.0.0
Requires-Dist: fastapi>=0.110.0
Requires-Dist: httpx>=0.28.1
Requires-Dist: inquirerpy>=0.3.4
Requires-Dist: jinja2>=3.1.3
Requires-Dist: json-repair>=0.7.0
Requires-Dist: langchain-community>=0.3.19
Requires-Dist: langchain-deepseek>=0.1.3
Requires-Dist: langchain-experimental>=0.3.4
Requires-Dist: langchain-mcp-adapters>=0.0.9
Requires-Dist: langchain-openai>=0.3.8
Requires-Dist: langchain-tavily<0.3
Requires-Dist: langgraph-checkpoint-mongodb>=0.1.4
Requires-Dist: langgraph-checkpoint-postgres==2.0.21
Requires-Dist: langgraph>=0.3.5
Requires-Dist: litellm>=1.63.11
Requires-Dist: markdownify>=1.1.0
Requires-Dist: mcp>=1.11.0
Requires-Dist: numpy>=2.2.3
Requires-Dist: pandas>=2.2.3
Requires-Dist: python-dotenv>=1.0.1
Requires-Dist: readabilipy>=0.3.0
Requires-Dist: socksio>=1.0.0
Requires-Dist: sse-starlette>=1.6.5
Requires-Dist: uvicorn>=0.27.1
Requires-Dist: wikipedia>=1.4.0
Requires-Dist: yfinance>=0.2.54
Provides-Extra: dev
Requires-Dist: langgraph-cli[inmem]>=0.2.10; extra == 'dev'
Requires-Dist: ruff; extra == 'dev'
Provides-Extra: test
Requires-Dist: pytest-asyncio>=1.0.0; extra == 'test'
Requires-Dist: pytest-cov>=4.1.0; extra == 'test'
Requires-Dist: pytest>=7.4.0; extra == 'test'
